{
  "timestamp": 1769005824.8433397,
  "rankings": [
    {
      "ticker": "GLD",
      "count": 36,
      "sentiment": 0.8
    },
    {
      "ticker": "MU",
      "count": 28,
      "sentiment": 0.4
    },
    {
      "ticker": "NFLX",
      "count": 21,
      "sentiment": -0.8
    },
    {
      "ticker": "SNDK",
      "count": 14,
      "sentiment": 0.8
    },
    {
      "ticker": "NVDA",
      "count": 12,
      "sentiment": 0.1
    },
    {
      "ticker": "FANG",
      "count": 12,
      "sentiment": -0.4
    },
    {
      "ticker": "IREN",
      "count": 6,
      "sentiment": -0.2
    },
    {
      "ticker": "GOOG",
      "count": 6,
      "sentiment": -0.1
    },
    {
      "ticker": "OKLO",
      "count": 5,
      "sentiment": 0.7
    },
    {
      "ticker": "LAES",
      "count": 5,
      "sentiment": 0.3
    }
  ],
  "fear_greed": 40,
  "radar": {
    "hype": 8,
    "panic": 7,
    "faith": 5,
    "gamble": 9,
    "iq": 2
  }
}